ariestools/__init__.py
ariestools/arg_util.py
ariestools/beauty_print.py
ariestools/color_output.py
ariestools/file_util.py
ariestools/graphql_query_util.py
ariestools/json_path_util.py
ariestools/json_util.py
ariestools/object.py
ariestools/path_util.py
ariestools/random_util.py
ariestools/time_util.py
ariestools/yaml_util.py
ariestools-1.7.12.dist-info/METADATA
ariestools-1.7.12.dist-info/WHEEL
ariestools-1.7.12.dist-info/top_level.txt
ariestools-1.7.12.dist-info/RECORD
