Metadata-Version: 2.1
Name: ariestools
Version: 1.7.12
Summary: Common Tools for python lib
Home-page: 
Author: jasonzhang
Author-email: qwertjkl9090@163.com
Classifier: License :: OSI Approved :: MIT License
Classifier: Intended Audience :: Developers
Classifier: Operating System :: OS Independent
Classifier: Programming Language :: Python :: 3.7
Requires-Dist: requests ==2.31.0
Requires-Dist: urllib3 ==2.1.0
Requires-Dist: PyYAML ==6.0.1
Requires-Dist: pendulum ==2.1.2
Requires-Dist: namedtupled ==0.3.3
Requires-Dist: hues ==0.2.2
Requires-Dist: tenacity ==8.2.3
